odoo10_addon_website_sale_cart_selectable-10.0.1.1.0-py2.7-nspkg.pth
odoo/addons/website_sale_cart_selectable/README.rst
odoo/addons/website_sale_cart_selectable/__init__.py
odoo/addons/website_sale_cart_selectable/__manifest__.py
odoo/addons/website_sale_cart_selectable/i18n/ca.po
odoo/addons/website_sale_cart_selectable/i18n/de.po
odoo/addons/website_sale_cart_selectable/i18n/es.po
odoo/addons/website_sale_cart_selectable/i18n/es_MX.po
odoo/addons/website_sale_cart_selectable/i18n/fi.po
odoo/addons/website_sale_cart_selectable/i18n/fr.po
odoo/addons/website_sale_cart_selectable/i18n/fr_CH.po
odoo/addons/website_sale_cart_selectable/i18n/hr.po
odoo/addons/website_sale_cart_selectable/i18n/hr_HR.po
odoo/addons/website_sale_cart_selectable/i18n/it.po
odoo/addons/website_sale_cart_selectable/i18n/nl_NL.po
odoo/addons/website_sale_cart_selectable/i18n/pt_BR.po
odoo/addons/website_sale_cart_selectable/i18n/ro.po
odoo/addons/website_sale_cart_selectable/i18n/sl.po
odoo/addons/website_sale_cart_selectable/i18n/tr_TR.po
odoo/addons/website_sale_cart_selectable/i18n/vi_VN.po
odoo/addons/website_sale_cart_selectable/i18n/zh_CN.po
odoo/addons/website_sale_cart_selectable/models/__init__.py
odoo/addons/website_sale_cart_selectable/models/product.py
odoo/addons/website_sale_cart_selectable/static/description/icon.png
odoo/addons/website_sale_cart_selectable/views/product_view.xml
odoo/addons/website_sale_cart_selectable/views/website_sale_template.xml
odoo10_addon_website_sale_cart_selectable-10.0.1.1.0.dist-info/DESCRIPTION.rst
odoo10_addon_website_sale_cart_selectable-10.0.1.1.0.dist-info/METADATA
odoo10_addon_website_sale_cart_selectable-10.0.1.1.0.dist-info/RECORD
odoo10_addon_website_sale_cart_selectable-10.0.1.1.0.dist-info/WHEEL
odoo10_addon_website_sale_cart_selectable-10.0.1.1.0.dist-info/metadata.json
odoo10_addon_website_sale_cart_selectable-10.0.1.1.0.dist-info/namespace_packages.txt
odoo10_addon_website_sale_cart_selectable-10.0.1.1.0.dist-info/top_level.txt
